admin_permissions/__init__.py
admin_permissions/admin.py
admin_permissions/apps.py
admin_permissions/models.py
django_admin_permissions-1.1.0.dist-info/LICENSE
django_admin_permissions-1.1.0.dist-info/METADATA
django_admin_permissions-1.1.0.dist-info/WHEEL
django_admin_permissions-1.1.0.dist-info/top_level.txt
django_admin_permissions-1.1.0.dist-info/RECORD
